fnctl/__init__.py
fnctl/cli.py
fnctl/runtime.py
fnctl/server.py
fnctl/utils.py
fnctl/templates/python/main.py
fnctl-0.1.1.dist-info/licenses/LICENSE
fnctl-0.1.1.dist-info/METADATA
fnctl-0.1.1.dist-info/WHEEL
fnctl-0.1.1.dist-info/entry_points.txt
fnctl-0.1.1.dist-info/top_level.txt
fnctl-0.1.1.dist-info/RECORD
